__init__.py
linux_do_connect.py
linux_do_connect_token-0.0.3.dist-info/METADATA
linux_do_connect_token-0.0.3.dist-info/WHEEL
linux_do_connect_token-0.0.3.dist-info/licenses/LICENSE
linux_do_connect_token-0.0.3.dist-info/RECORD
