Metadata-Version: 2.4
Name: linux-do-connect-token
Version: 0.0.3
Summary: A helper library to authenticate with connect.linux.do and retrieve auth.session-token
License: MIT
License-File: LICENSE
Author: Sn0wo2
Requires-Python: >=3.12
Classifier: License :: OSI Approved :: MIT License
Classifier: Programming Language :: Python :: 3
Classifier: Programming Language :: Python :: 3.12
Classifier: Programming Language :: Python :: 3.13
Classifier: Programming Language :: Python :: 3.14
Requires-Dist: curl-cffi (>=0.14.0,<0.15.0)
